centraal_client_flow/__init__.py
centraal_client_flow/connections/__init__.py
centraal_client_flow/connections/cosmosdb.py
centraal_client_flow/connections/service_bus.py
centraal_client_flow/events/__init__.py
centraal_client_flow/events/processor.py
centraal_client_flow/events/receiver.py
centraal_client_flow/events/timer.py
centraal_client_flow/helpers/__init__.py
centraal_client_flow/helpers/cosmos.py
centraal_client_flow/helpers/logger.py
centraal_client_flow/helpers/pydantic.py
centraal_client_flow/models/schemas.py
centraal_client_flow/py.typed
centraal_client_flow/rules/__init__.py
centraal_client_flow/rules/integration/__init__.py
centraal_client_flow/rules/integration/processor.py
centraal_client_flow/rules/integration/strategy.py
centraal_client_flow/rules/integration/v2.py
centraal_client_flow/rules/update.py
centraal_client_flow-0.1.17.dist-info/AUTHORS.md
centraal_client_flow-0.1.17.dist-info/LICENSE
centraal_client_flow-0.1.17.dist-info/METADATA
centraal_client_flow-0.1.17.dist-info/WHEEL
centraal_client_flow-0.1.17.dist-info/RECORD
